ipyopenlayers/__init__.py
ipyopenlayers/_frontend.py
ipyopenlayers/_version.py
ipyopenlayers/openlayers.py
ipyopenlayers/labextension/package.json
ipyopenlayers/labextension/static/10.992cfbdb71e0f1167830.js
ipyopenlayers/labextension/static/10.992cfbdb71e0f1167830.js.LICENSE.txt
ipyopenlayers/labextension/static/114.45ee2138d693ede9b783.js
ipyopenlayers/labextension/static/122.fdc5f9205a5b7f2708e9.js
ipyopenlayers/labextension/static/308.68046a0d364e0e60929a.js
ipyopenlayers/labextension/static/459.7202a6112e6689a0d185.js
ipyopenlayers/labextension/static/467.f3336d12daa3897c23a9.js
ipyopenlayers/labextension/static/509.3df96988358cdd6bbe96.js
ipyopenlayers/labextension/static/515.9b0ba8e4b237b97003c4.js
ipyopenlayers/labextension/static/542.353744f993c9be7dbb50.js
ipyopenlayers/labextension/static/581.8fbb709ef7d37ec42512.js
ipyopenlayers/labextension/static/591.1eeb147f4f91db685ce2.js
ipyopenlayers/labextension/static/647.e821c31c288bc4e44a4c.js
ipyopenlayers/labextension/static/698.9e0e1780bdd430b8d7d8.js
ipyopenlayers/labextension/static/698.9e0e1780bdd430b8d7d8.js.LICENSE.txt
ipyopenlayers/labextension/static/798.f7eb3c42ea2b6b16466d.js
ipyopenlayers/labextension/static/925.326782c646170f429b91.js
ipyopenlayers/labextension/static/remoteEntry.15e04ddd0b33bcd164a3.js
ipyopenlayers/labextension/static/style.js
ipyopenlayers/labextension/static/third-party-licenses.json
ipyopenlayers/nbextension/extension.js
ipyopenlayers/nbextension/index.js
ipyopenlayers/nbextension/index.js.LICENSE.txt
ipyopenlayers/nbextension/index.js.map
ipyopenlayers/tests/__init__.py
ipyopenlayers/tests/conftest.py
ipyopenlayers/tests/test_example.py
ipyopenlayers/tests/test_nbextension_path.py
ipyopenlayers-0.2.1.data/data/share/jupyter/labextensions/ipyopenlayers/package.json
ipyopenlayers-0.2.1.data/data/share/jupyter/labextensions/ipyopenlayers/static/10.992cfbdb71e0f1167830.js
ipyopenlayers-0.2.1.dist-info/METADATA
ipyopenlayers-0.2.1.dist-info/WHEEL
ipyopenlayers-0.2.1.dist-info/licenses/LICENSE.txt
ipyopenlayers-0.2.1.dist-info/RECORD
